{
 "id": "fek:ΦΕΚ 62/Α/9-3-2000",
 "source": "catalog",
 "source_label": "ΦΕΚ (κατάλογος e-nomothesia)",
 "title": "Κύρωση ΠΝΠ για ομαλή λειτουργία δημόσιων σχολείων Α/βάθμιας & Β/βάθμιας (καταλήψεις)",
 "summary": "Κυρώνει ΠΝΠ που ποινικοποιεί παρεμπόδιση λειτουργίας σχολείων· χωρίς ένδειξη κατάργησης στο κείμενο.",
 "doc_type": "Νόμος",
 "fek_label": "ΦΕΚ 62/Α/9-3-2000",
 "date": "2000-03-09",
 "ada": null,
 "categories": [
  "Οργάνωση & Διοίκηση Σχολείων",
  "Σχολική Ζωή & Φοίτηση Μαθητών"
 ],
 "levels": [
  "Όλες / Γενικό"
 ],
 "classified_by": "ai-curated",
 "official_url": "https://ia37rg02wpsa01.blob.core.windows.net/fek/01/2000/20000100062.pdf",
 "source_url": "https://www.e-nomothesia.gr/kat-ekpaideuse/n-2811-2000.html",
 "added_at": "2026-06-27",
 "summary_ai": null,
 "keywords": [],
 "articles": [],
 "excerpts": [],
 "enriched": false,
 "status": "ΙΣΧΥΟΝ",
 "enrich_tried": 0,
 "affected_by": [],
 "authority_level": "primary_law",
 "verification_status": "verified",
 "legal_disclaimer_required": false,
 "doc_id": "8177835ff2921435",
 "year": "2000"
}