{
 "id": "fek:ΦΕΚ 1801/Β/11-4-2025",
 "source": "catalog",
 "source_label": "ΦΕΚ (κατάλογος e-nomothesia)",
 "title": "Διαπιστωτική αντιστοίχιση κλάδων & διαγνωστικές εξετάσεις ΣΤ΄ Δημοτικού/Γ΄ Γυμνασίου",
 "summary": "Πρόσφατη ρύθμιση (2025)",
 "doc_type": "Υπουργική Απόφαση",
 "fek_label": "ΦΕΚ 1801/Β/11-4-2025",
 "date": "2025-04-11",
 "ada": null,
 "categories": [
  "Τοποθετήσεις & Οργανικές Θέσεις",
  "Σχολική Ζωή & Φοίτηση Μαθητών"
 ],
 "levels": [
  "Όλες / Γενικό"
 ],
 "classified_by": "ai-curated",
 "official_url": "https://ia37rg02wpsa01.blob.core.windows.net/fek/02/2025/20250201801.pdf",
 "source_url": "https://www.e-nomothesia.gr/protobathmia-ekpaideuse/ya-38640-gd4-2025.html",
 "added_at": "2026-06-27",
 "summary_ai": null,
 "keywords": [],
 "articles": [],
 "excerpts": [],
 "enriched": false,
 "status": "ΙΣΧΥΟΝ",
 "enrich_tried": 0,
 "affected_by": [],
 "authority_level": "primary_law",
 "verification_status": "verified",
 "legal_disclaimer_required": false,
 "doc_id": "6c550f31f5592d2b",
 "year": "2025"
}