{
 "id": "fek:ΦΕΚ 4589/Β/22-8-2025",
 "source": "e-nomothesia",
 "source_label": "e-nomothesia.gr",
 "title": "Υπουργική Απόφαση 7612/2025 - ΦΕΚ 4589/Β/22-8-2025",
 "summary": "Αναστολή λειτουργίας Νηπιαγωγείων και Δημοτικών Σχολείων Περιφέρειας Πελοποννήσου για το σχολικό έτος 2025-2026.",
 "doc_type": "Υπουργική Απόφαση",
 "fek_label": "ΦΕΚ 4589/Β/22-8-2025",
 "date": "2025-08-22",
 "ada": null,
 "categories": [
  "Οργάνωση & Διοίκηση Σχολείων",
  "Νηπιαγωγείο / Ολοήμερο"
 ],
 "levels": [
  "Πρωτοβάθμια"
 ],
 "classified_by": "rules",
 "official_url": "https://ia37rg02wpsa01.blob.core.windows.net/fek/02/2025/20250204589.pdf",
 "source_url": "https://www.e-nomothesia.gr/kat-ekpaideuse/protobathmia-ekpaideuse/ya-7612-2025.html",
 "added_at": "2026-06-14",
 "summary_ai": null,
 "keywords": [],
 "articles": [],
 "excerpts": [],
 "enriched": false,
 "status": null,
 "enrich_tried": 1,
 "affected_by": [],
 "authority_level": "primary_law",
 "verification_status": "verified",
 "legal_disclaimer_required": false,
 "doc_id": "ef4d99d23c3c4f81",
 "year": "2025"
}