{
 "id": "fek:ΦΕΚ 2876/Β/9-9-2016",
 "source": "catalog",
 "source_label": "ΦΕΚ (κατάλογος e-nomothesia)",
 "title": "Καθορισμός Τομέων ΕΠΑ.Λ. Σιβιτανιδείου & πανελλ. μαθήματα",
 "summary": "Πολυθεματικό",
 "doc_type": "Υπουργική Απόφαση",
 "fek_label": "ΦΕΚ 2876/Β/9-9-2016",
 "date": "2016-09-09",
 "ada": null,
 "categories": [
  "ΕΠΑΛ / Επαγγελματική Εκπαίδευση",
  "Εξετάσεις & Εισαγωγή στην Τριτοβάθμια"
 ],
 "levels": [
  "Δευτεροβάθμια"
 ],
 "classified_by": "ai-curated",
 "official_url": "https://ia37rg02wpsa01.blob.core.windows.net/fek/02/2016/20160202876.pdf",
 "source_url": "https://www.e-nomothesia.gr/deuterobathmia-ekpaideuse/upourgike-apophase-ph-151-144437-a5-2016.html",
 "added_at": "2026-06-27",
 "summary_ai": null,
 "keywords": [],
 "articles": [],
 "excerpts": [],
 "enriched": false,
 "status": "ΙΣΧΥΟΝ",
 "enrich_tried": 0,
 "affected_by": [],
 "authority_level": "primary_law",
 "verification_status": "verified",
 "legal_disclaimer_required": false,
 "doc_id": "c0d661465322853e",
 "year": "2016"
}