{
 "id": "ada:929Γ46ΝΚΠΔ-ΔΑ9",
 "source": "diavgeia",
 "source_label": "Διαύγεια · Υπουργείο Παιδείας, Θρησκευμάτων & Αθλητισμού",
 "title": "ΕΓΓΡΑΦΗ ΣΤΟΝ ΕΙΔΙΚΟ ΠΙΝΑΚΑ ΑΘΛΗΤΩΝ",
 "summary": "ΕΓΓΡΑΦΗ ΣΤΟΝ ΕΙΔΙΚΟ ΠΙΝΑΚΑ ΑΘΛΗΤΩΝ",
 "doc_type": "Κανονιστική Πράξη",
 "fek_label": null,
 "date": "2026-06-15",
 "ada": "929Γ46ΝΚΠΔ-ΔΑ9",
 "categories": [
  "Σχολική Ζωή & Φοίτηση Μαθητών"
 ],
 "levels": [
  "Όλες / Γενικό"
 ],
 "classified_by": "rules",
 "official_url": "https://diavgeia.gov.gr/doc/929Γ46ΝΚΠΔ-ΔΑ9",
 "source_url": "https://diavgeia.gov.gr/decision/view/929Γ46ΝΚΠΔ-ΔΑ9",
 "added_at": "2026-06-17",
 "summary_ai": null,
 "keywords": [],
 "articles": [],
 "excerpts": [],
 "enriched": false,
 "status": null,
 "enrich_tried": 1,
 "affected_by": [],
 "authority_level": "diavgeia_decision",
 "verification_status": "verified",
 "legal_disclaimer_required": false,
 "doc_id": "055273c02433e6d9",
 "year": "2026"
}